get_random_word/__init__.py
get_random_word/get_random.py
get_random_word-0.0.6.dist-info/METADATA
get_random_word-0.0.6.dist-info/WHEEL
get_random_word-0.0.6.dist-info/top_level.txt
get_random_word-0.0.6.dist-info/RECORD
